[
  {
    "基本情報": {
      "ID": "100335",
      "名前": "ハウル",
      "サブネーム": "狂気のシャーマン",
      "所属": "龍の遺跡",
      "フレーバーテキスト": "禁じられた魔法を使い続けたハウルは完全に理性を失った。\\nしかし同時に、究極の魔力を手に入れることができた。",
      "レアリティ": "上級",
      "星": "5",
      "最大星": "5",
      "タイプ": "支援型",
      "タイプID": "4",
      "射程": "遠距離",
      "武器タイプ": "魔法武器"
    },
    "ステータス": {
      "物理攻撃力": "0",
      "魔法攻撃力": "113",
      "防御力": "69",
      "HP": "468",
      "敏捷性": "12",
      "クリティカル率": "50",
      "与クリティカルダメージ": "1500",
      "フェイタルヒット率": "0",
      "ブロック率": "0",
      "被ダメージ減少": 0,
      "デバフ回避妨害率": "0",
      "デバフ回避率": "0"
    },
    "成長データ": {
      "攻撃力タイプ": "魔法攻撃力",
      "レベル1": {
        "魔法攻撃力": 113,
        "防御力": 69,
        "HP": 468
      },
      "レベル30": {
        "魔法攻撃力": 519,
        "防御力": 301,
        "HP": 2092
      },
      "レベルアップ上昇値": {
        "魔法攻撃力": 14,
        "防御力": 8,
        "HP": 56
      },
      "強化上昇値": {
        "魔法攻撃力": 34,
        "防御力": 22,
        "HP": 140
      },
      "強化段階別": {
        "+0": {
          "魔法攻撃力": 519,
          "防御力": 301,
          "HP": 2092
        },
        "+1": {
          "魔法攻撃力": 553,
          "防御力": 323,
          "HP": 2232
        },
        "+2": {
          "魔法攻撃力": 587,
          "防御力": 345,
          "HP": 2372
        },
        "+3": {
          "魔法攻撃力": 621,
          "防御力": 367,
          "HP": 2512
        },
        "+4": {
          "魔法攻撃力": 655,
          "防御力": 389,
          "HP": 2652
        },
        "+5": {
          "魔法攻撃力": 689,
          "防御力": 411,
          "HP": 2792
        }
      },
      "強化コスト": [
        {
          "段階": 0,
          "コスト": 4400
        },
        {
          "段階": 1,
          "コスト": 5400
        },
        {
          "段階": 2,
          "コスト": 6400
        },
        {
          "段階": 3,
          "コスト": 7400
        },
        {
          "段階": 4,
          "コスト": 8400
        }
      ]
    },
    "経験値": {
      "最大レベル累計": 123900
    },
    "潜在能力解放": {
      "available": true,
      "タイプ別": {},
      "解放条件": [],
      "合計上昇値": {}
    },
    "スキル情報": {
      "通常攻撃": {
        "id": "10033501",
        "name": "",
        "desc": "敵1体\n - 魔法攻撃力の90%のダメージを1回与える\nスキル強化効果\n - ダメージ上昇：物理攻撃力の90%になる",
        "cooltime": "",
        "icon": "images/icon/SkillIcon_PC/Tex_Skill_1003301.png"
      },
      "スキル1": {
        "id": "10033502",
        "name": "感電",
        "desc": "敵1体\n - 魔法攻撃力の245%のダメージを1回与える\n - バフ解除2個[確率100%]\nスキル強化効果\n - ダメージ上昇：物理攻撃力の245%になる",
        "cooltime": "⏱️ CT: 60秒",
        "icon": "images/icon/SkillIcon_PC/Tex_Skill_1003302.png"
      },
      "スキル2": {
        "id": "10033503",
        "name": "戦意高揚",
        "desc": "すべての味方\n - 与ダメージ上昇[3ターン継続]",
        "cooltime": "⏱️ CT: 80秒",
        "icon": "images/icon/SkillIcon_PC/Tex_Skill_1003303.png"
      },
      "パッシブ": {
        "id": "10033504",
        "name": "禁じられた魔法",
        "desc": "自身\n - 戦闘不能時、HPが60%の状態で復活(戦闘中1回のみ発動)",
        "cooltime": "",
        "icon": "images/icon/SkillIcon_PC/Tex_Skill_1003304.png"
      }
    },
    "超越解放効果": {},
    "プロフィール": {
      "ストーリー": "ハウルは龍の遺跡に棲む、高い知能を持つブタの獣人だ。\\nブタの獣人たちは力が弱く動きが鈍いため、他の獣人に食い殺されたり家畜のように扱われた。\\nだが龍の遺跡に棲むブタの獣人たちは、ここを管理するジェイブのおかげで餌になることはなかった。\\nだがジェイブも領民の間での殺傷行為を止めていただけで、弱肉強食の摂理を完全に無視したわけではなかったので、ブタの獣人たちは厳しい生活を余儀なくされた。\\n結局、そんな暮らしに耐えられなくなったハウルは、禁じられた魔法を研究して恐ろしい力を手に入れた。\\nだが危険な力を手に入れた代償として、彼自身も気づかないうちに理性を失っていた。"
    }
  },
  {
    "基本情報": {
      "ID": "100334",
      "名前": "ハウル",
      "サブネーム": "魔力持ちのシャーマン",
      "所属": "龍の遺跡",
      "フレーバーテキスト": "禁じられた魔法を研究した末、強力な魔力を手に入れた。\\nしかしその代償として理性を徐々に失いつつある。",
      "レアリティ": "上級",
      "星": "4",
      "最大星": "5",
      "タイプ": "支援型",
      "タイプID": "4",
      "射程": "遠距離",
      "武器タイプ": "魔法武器"
    },
    "ステータス": {
      "物理攻撃力": "0",
      "魔法攻撃力": "81",
      "防御力": "49",
      "HP": "334",
      "敏捷性": "10",
      "クリティカル率": "50",
      "与クリティカルダメージ": "1500",
      "フェイタルヒット率": "0",
      "ブロック率": "0",
      "被ダメージ減少": 0,
      "デバフ回避妨害率": "0",
      "デバフ回避率": "0"
    },
    "成長データ": {
      "攻撃力タイプ": "魔法攻撃力",
      "レベル1": {
        "魔法攻撃力": 81,
        "防御力": 49,
        "HP": 334
      },
      "レベル30": {
        "魔法攻撃力": 371,
        "防御力": 194,
        "HP": 1494
      },
      "レベルアップ上昇値": {
        "魔法攻撃力": 10,
        "防御力": 5,
        "HP": 40
      },
      "強化上昇値": {
        "魔法攻撃力": 24,
        "防御力": 16,
        "HP": 100
      },
      "強化段階別": {
        "+0": {
          "魔法攻撃力": 371,
          "防御力": 194,
          "HP": 1494
        },
        "+1": {
          "魔法攻撃力": 395,
          "防御力": 210,
          "HP": 1594
        },
        "+2": {
          "魔法攻撃力": 419,
          "防御力": 226,
          "HP": 1694
        },
        "+3": {
          "魔法攻撃力": 443,
          "防御力": 242,
          "HP": 1794
        },
        "+4": {
          "魔法攻撃力": 467,
          "防御力": 258,
          "HP": 1894
        },
        "+5": {
          "魔法攻撃力": 491,
          "防御力": 274,
          "HP": 1994
        }
      },
      "強化コスト": [
        {
          "段階": 0,
          "コスト": 2800
        },
        {
          "段階": 1,
          "コスト": 3600
        },
        {
          "段階": 2,
          "コスト": 4400
        },
        {
          "段階": 3,
          "コスト": 5200
        },
        {
          "段階": 4,
          "コスト": 6000
        }
      ]
    },
    "経験値": {
      "最大レベル累計": 123900
    },
    "潜在能力解放": {
      "available": true,
      "タイプ別": {},
      "解放条件": [],
      "合計上昇値": {}
    },
    "スキル情報": {
      "通常攻撃": {
        "id": "10033401",
        "name": "",
        "desc": "敵1体\n - 魔法攻撃力の80%のダメージを1回与える\nスキル強化効果\n - ダメージ上昇：物理攻撃力の80%になる",
        "cooltime": "",
        "icon": "images/icon/SkillIcon_PC/Tex_Skill_1003301.png"
      },
      "スキル1": {
        "id": "10033402",
        "name": "感電",
        "desc": "敵1体\n - 魔法攻撃力の220%のダメージを1回与える\n - バフ解除1個[確率100%]\nスキル強化効果\n - ダメージ上昇：物理攻撃力の220%になる",
        "cooltime": "⏱️ CT: 60秒",
        "icon": "images/icon/SkillIcon_PC/Tex_Skill_1003302.png"
      },
      "スキル2": {
        "id": "10033403",
        "name": "戦意高揚",
        "desc": "すべての味方\n - 与ダメージ上昇[3ターン継続]",
        "cooltime": "⏱️ CT: 80秒",
        "icon": "images/icon/SkillIcon_PC/Tex_Skill_1003303.png"
      },
      "パッシブ": {
        "id": "10033404",
        "name": "禁じられた魔法",
        "desc": "自身\n - 戦闘不能時、HPが45%の状態で復活(戦闘中1回のみ発動)",
        "cooltime": "",
        "icon": "images/icon/SkillIcon_PC/Tex_Skill_1003304.png"
      }
    },
    "超越解放効果": {},
    "プロフィール": {
      "ストーリー": "ハウルは龍の遺跡に棲む、高い知能を持つブタの獣人だ。\\nブタの獣人たちは力が弱く動きが鈍いため、他の獣人に食い殺されたり家畜のように扱われた。\\nだが龍の遺跡に棲むブタの獣人たちは、ここを管理するジェイブのおかげで餌になることはなかった。\\nだがジェイブも領民の間での殺傷行為を止めていただけで、弱肉強食の摂理を完全に無視したわけではなかったので、ブタの獣人たちは厳しい生活を余儀なくされた。\\n結局、そんな暮らしに耐えられなくなったハウルは、禁じられた魔法を研究して恐ろしい力を手に入れた。\\nだが危険な力を手に入れた代償として、彼自身も気づかないうちに理性を失っていた。"
    }
  },
  {
    "基本情報": {
      "ID": "100333",
      "名前": "ハウル",
      "サブネーム": "シャーマン",
      "所属": "龍の遺跡",
      "フレーバーテキスト": "龍の遺跡の東に住む、高い知能を持ったブタ。\\n禁じられた魔法を研究するシャーマンである。",
      "レアリティ": "上級",
      "星": "3",
      "最大星": "5",
      "タイプ": "支援型",
      "タイプID": "4",
      "射程": "遠距離",
      "武器タイプ": "魔法武器"
    },
    "ステータス": {
      "物理攻撃力": "0",
      "魔法攻撃力": "63",
      "防御力": "38",
      "HP": "261",
      "敏捷性": "8",
      "クリティカル率": "50",
      "与クリティカルダメージ": "1500",
      "フェイタルヒット率": "0",
      "ブロック率": "0",
      "被ダメージ減少": 0,
      "デバフ回避妨害率": "0",
      "デバフ回避率": "0"
    },
    "成長データ": {
      "攻撃力タイプ": "魔法攻撃力",
      "レベル1": {
        "魔法攻撃力": 63,
        "防御力": 38,
        "HP": 261
      },
      "レベル30": {
        "魔法攻撃力": 295,
        "防御力": 183,
        "HP": 1160
      },
      "レベルアップ上昇値": {
        "魔法攻撃力": 8,
        "防御力": 5,
        "HP": 31
      },
      "強化上昇値": {
        "魔法攻撃力": 13,
        "防御力": 8,
        "HP": 52
      },
      "強化段階別": {
        "+0": {
          "魔法攻撃力": 295,
          "防御力": 183,
          "HP": 1160
        },
        "+1": {
          "魔法攻撃力": 308,
          "防御力": 191,
          "HP": 1212
        },
        "+2": {
          "魔法攻撃力": 321,
          "防御力": 199,
          "HP": 1264
        },
        "+3": {
          "魔法攻撃力": 334,
          "防御力": 207,
          "HP": 1316
        },
        "+4": {
          "魔法攻撃力": 347,
          "防御力": 215,
          "HP": 1368
        },
        "+5": {
          "魔法攻撃力": 360,
          "防御力": 223,
          "HP": 1420
        }
      },
      "強化コスト": [
        {
          "段階": 0,
          "コスト": 1600
        },
        {
          "段階": 1,
          "コスト": 2200
        },
        {
          "段階": 2,
          "コスト": 2800
        },
        {
          "段階": 3,
          "コスト": 3400
        },
        {
          "段階": 4,
          "コスト": 4000
        }
      ]
    },
    "経験値": {
      "最大レベル累計": 123900
    },
    "潜在能力解放": {
      "available": true,
      "タイプ別": {},
      "解放条件": [],
      "合計上昇値": {}
    },
    "スキル情報": {
      "通常攻撃": {
        "id": "10033301",
        "name": "",
        "desc": "敵1体\n - 魔法攻撃力の80%のダメージを1回与える\nスキル強化効果\n - ダメージ上昇：物理攻撃力の80%になる",
        "cooltime": "",
        "icon": "images/icon/SkillIcon_PC/Tex_Skill_1003301.png"
      },
      "スキル1": {
        "id": "10033302",
        "name": "感電",
        "desc": "敵1体\n - 魔法攻撃力の200%のダメージを1回与える\n - バフ解除1個[確率100%]\nスキル強化効果\n - ダメージ上昇：物理攻撃力の200%になる",
        "cooltime": "⏱️ CT: 60秒",
        "icon": "images/icon/SkillIcon_PC/Tex_Skill_1003302.png"
      },
      "スキル2": {
        "id": "10033303",
        "name": "戦意高揚",
        "desc": "すべての味方\n - 与ダメージ上昇[3ターン継続]",
        "cooltime": "⏱️ CT: 80秒",
        "icon": "images/icon/SkillIcon_PC/Tex_Skill_1003303.png"
      },
      "パッシブ": {
        "id": "10033304",
        "name": "禁じられた魔法",
        "desc": "自身\n - 戦闘不能時、HPが30%の状態で復活(戦闘中1回のみ発動)",
        "cooltime": "",
        "icon": "images/icon/SkillIcon_PC/Tex_Skill_1003304.png"
      }
    },
    "超越解放効果": {},
    "プロフィール": {
      "ストーリー": "ハウルは龍の遺跡に棲む、高い知能を持つブタの獣人だ。\\nブタの獣人たちは力が弱く動きが鈍いため、他の獣人に食い殺されたり家畜のように扱われた。\\nだが龍の遺跡に棲むブタの獣人たちは、ここを管理するジェイブのおかげで餌になることはなかった。\\nだがジェイブも領民の間での殺傷行為を止めていただけで、弱肉強食の摂理を完全に無視したわけではなかったので、ブタの獣人たちは厳しい生活を余儀なくされた。\\n結局、そんな暮らしに耐えられなくなったハウルは、禁じられた魔法を研究して恐ろしい力を手に入れた。\\nだが危険な力を手に入れた代償として、彼自身も気づかないうちに理性を失っていた。"
    }
  }
]