[
  {
    "基本情報": {
      "ID": "101736",
      "名前": "水篠旬",
      "サブネーム": "「影の君主」",
      "所属": "",
      "フレーバーテキスト": "水篠旬は転職クエストをクリアして「ネクロマンサー」となった。そして、その後の残りポイントが条件を満たしていたため、すぐに「影の君主」へと二次転職することができた。",
      "レアリティ": "伝説+",
      "星": "6",
      "最大星": "6",
      "タイプ": "",
      "タイプID": "0",
      "射程": "",
      "武器タイプ": "",
      "未実装": true
    },
    "ステータス": {
      "物理攻撃力": "0",
      "魔法攻撃力": "239",
      "防御力": "92",
      "HP": "535",
      "敏捷性": "29",
      "クリティカル率": "50",
      "与クリティカルダメージ": "1500",
      "フェイタルヒット率": "0",
      "ブロック率": "0",
      "被ダメージ減少": 0,
      "デバフ回避妨害率": "0",
      "デバフ回避率": "0"
    },
    "成長データ": {
      "攻撃力タイプ": "魔法攻撃力",
      "レベル1": {
        "魔法攻撃力": 239,
        "防御力": 92,
        "HP": 535
      },
      "レベル30": {
        "魔法攻撃力": 1080,
        "防御力": 411,
        "HP": 2391
      },
      "レベルアップ上昇値": {
        "魔法攻撃力": 29,
        "防御力": 11,
        "HP": 64
      },
      "強化上昇値": {
        "魔法攻撃力": 84,
        "防御力": 32,
        "HP": 187
      },
      "強化段階別": {
        "+0": {
          "魔法攻撃力": 1080,
          "防御力": 411,
          "HP": 2391
        },
        "+1": {
          "魔法攻撃力": 1164,
          "防御力": 443,
          "HP": 2578
        },
        "+2": {
          "魔法攻撃力": 1248,
          "防御力": 475,
          "HP": 2765
        },
        "+3": {
          "魔法攻撃力": 1332,
          "防御力": 507,
          "HP": 2952
        },
        "+4": {
          "魔法攻撃力": 1416,
          "防御力": 539,
          "HP": 3139
        },
        "+5": {
          "魔法攻撃力": 1500,
          "防御力": 571,
          "HP": 3326
        }
      },
      "強化コスト": [
        {
          "段階": 0,
          "コスト": 6400
        },
        {
          "段階": 1,
          "コスト": 7600
        },
        {
          "段階": 2,
          "コスト": 8000
        },
        {
          "段階": 3,
          "コスト": 10000
        },
        {
          "段階": 4,
          "コスト": 11200
        }
      ]
    },
    "経験値": {
      "最大レベル累計": 123900
    },
    "潜在能力解放": {
      "available": false
    },
    "スキル情報": {
      "通常攻撃": {
        "id": "10173601",
        "name": "",
        "desc": "敵1体\n - 魔法攻撃力の100%のダメージを1回与える\nスキル強化効果\n - ダメージ上昇：魔法攻撃力の130%になる",
        "cooltime": "",
        "icon": "images/icon/SkillIcon_PC/Tex_Skill_1017301.webp"
      },
      "スキル1": {
        "id": "10173602",
        "name": "急所突き",
        "desc": "敵4体\nスキル強化効果\n - ダメージ上昇：魔法攻撃力の67%+対象の最大HPの9%になる",
        "cooltime": "⏱️ CT: 96秒",
        "icon": "images/icon/SkillIcon_PC/Tex_Skill_1017302.webp"
      },
      "スキル2": {
        "id": "10173603",
        "name": "影の召喚",
        "desc": "すべての敵\n - 魔法攻撃力の45%の防御無視ダメージを2回与える\nスキル強化効果\n - ダメージ上昇：魔法攻撃力の55%になる",
        "cooltime": "⏱️ CT: 104秒",
        "icon": "images/icon/SkillIcon_PC/Tex_Skill_1017303.webp"
      },
      "パッシブ": {
        "id": "10173604",
        "name": "レベルアップ",
        "desc": "すべての味方\n - 与魔法ダメージ上昇[常時]\n自身\n - すべてのダメージ無効化[敵から攻撃を3回受けるまで]\n - 戦闘不能時、HPが80%の状態で復活(戦闘中1回のみ発動)\n - 逆境を勝ち抜いた者[常時]\n - デバフ回避率上昇[常時]\n - 自分の通常攻撃2回発動時、レベルが1上昇[最大30上昇]\n - 自分のスキル1回発動時、レベルが1上昇[最大30上昇]\n - 敵が戦闘不能時、レベルが2上昇[最大30上昇]\nスキル強化効果\n - 効果上昇：与魔法ダメージ上昇の効果が20%になる\n - 効果上昇：復活時のHPが最大HPの100%になる\n - 効果上昇：デバフ回避率上昇の効果が49%になる\n超越2段階達成効果\n自身\n超越6段階達成効果\nすべての味方\n - 効果追加：自分が復活時、すべてのダメージ無効化[1回攻撃を受けるまで]\n自身\n - 効果追加：自分が復活時、すべてのダメージ無効化[3回攻撃を受けるまで]",
        "cooltime": "",
        "icon": "images/icon/SkillIcon_PC/Tex_Skill_1017304.webp"
      }
    },
    "超越解放効果": {},
    "プロフィール": {}
  },
  {
    "基本情報": {
      "ID": "101735",
      "名前": "水篠旬",
      "サブネーム": "逆境を勝ち抜いた者",
      "所属": "",
      "フレーバーテキスト": "水篠旬は絶え間なく押し寄せてくる鎧の魔獣たちとの戦いで、\\n何度も死線を越えながら戦い抜いた末に生き残った。",
      "レアリティ": "伝説+",
      "星": "5",
      "最大星": "6",
      "タイプ": "",
      "タイプID": "0",
      "射程": "",
      "武器タイプ": "",
      "未実装": true
    },
    "ステータス": {
      "物理攻撃力": "0",
      "魔法攻撃力": "171",
      "防御力": "66",
      "HP": "382",
      "敏捷性": "26",
      "クリティカル率": "50",
      "与クリティカルダメージ": "1500",
      "フェイタルヒット率": "0",
      "ブロック率": "0",
      "被ダメージ減少": 0,
      "デバフ回避妨害率": "0",
      "デバフ回避率": "0"
    },
    "成長データ": {
      "攻撃力タイプ": "魔法攻撃力",
      "レベル1": {
        "魔法攻撃力": 171,
        "防御力": 66,
        "HP": 382
      },
      "レベル30": {
        "魔法攻撃力": 780,
        "防御力": 298,
        "HP": 1716
      },
      "レベルアップ上昇値": {
        "魔法攻撃力": 21,
        "防御力": 8,
        "HP": 46
      },
      "強化上昇値": {
        "魔法攻撃力": 60,
        "防御力": 22,
        "HP": 134
      },
      "強化段階別": {
        "+0": {
          "魔法攻撃力": 780,
          "防御力": 298,
          "HP": 1716
        },
        "+1": {
          "魔法攻撃力": 840,
          "防御力": 320,
          "HP": 1850
        },
        "+2": {
          "魔法攻撃力": 900,
          "防御力": 342,
          "HP": 1984
        },
        "+3": {
          "魔法攻撃力": 960,
          "防御力": 364,
          "HP": 2118
        },
        "+4": {
          "魔法攻撃力": 1020,
          "防御力": 386,
          "HP": 2252
        },
        "+5": {
          "魔法攻撃力": 1080,
          "防御力": 408,
          "HP": 2386
        }
      },
      "強化コスト": [
        {
          "段階": 0,
          "コスト": 4400
        },
        {
          "段階": 1,
          "コスト": 5400
        },
        {
          "段階": 2,
          "コスト": 6400
        },
        {
          "段階": 3,
          "コスト": 7400
        },
        {
          "段階": 4,
          "コスト": 8400
        }
      ]
    },
    "経験値": {
      "最大レベル累計": 123900
    },
    "潜在能力解放": {
      "available": false
    },
    "スキル情報": {
      "通常攻撃": {
        "id": "10173501",
        "name": "",
        "desc": "敵1体\n - 魔法攻撃力の90%のダメージを1回与える\nスキル強化効果\n - ダメージ上昇：物理攻撃力の90%になる",
        "cooltime": "",
        "icon": "images/icon/SkillIcon_PC/Tex_Skill_1017301.webp"
      },
      "スキル1": {
        "id": "10173502",
        "name": "急所突き",
        "desc": "敵4体\nスキル強化効果\n - ダメージ上昇：物理攻撃力の52%になる",
        "cooltime": "⏱️ CT: 96秒",
        "icon": "images/icon/SkillIcon_PC/Tex_Skill_1017302.webp"
      },
      "スキル2": {
        "id": "10173503",
        "name": "影の召喚",
        "desc": "すべての敵\n - 魔法攻撃力の42%の防御無視ダメージを2回与える\nスキル強化効果\n - ダメージ上昇：物理攻撃力の42%になる",
        "cooltime": "⏱️ CT: 104秒",
        "icon": "images/icon/SkillIcon_PC/Tex_Skill_1017303.webp"
      },
      "パッシブ": {
        "id": "10173504",
        "name": "レベルアップ",
        "desc": "すべての味方\n - 与魔法ダメージ上昇[常時]\n自身\n - すべてのダメージ無効化[敵から攻撃を3回受けるまで]\n - 戦闘不能時、HPが60%の状態で復活(戦闘中1回のみ発動)\n - 逆境を勝ち抜いた者[常時]\n - デバフ回避率上昇[常時]\n - 自分の通常攻撃2回発動時、レベルが1上昇[最大30上昇]\n - 自分のスキル1回発動時、レベルが1上昇[最大30上昇]\n - 敵が戦闘不能時、レベルが2上昇[最大30上昇]\nスキル強化効果\n - 効果上昇：デバフ回避率上昇の効果が31%になる",
        "cooltime": "",
        "icon": "images/icon/SkillIcon_PC/Tex_Skill_1017304.webp"
      }
    },
    "超越解放効果": {},
    "プロフィール": {}
  },
  {
    "基本情報": {
      "ID": "101734",
      "名前": "水篠旬",
      "サブネーム": "狼虐殺者",
      "所属": "",
      "フレーバーテキスト": "システムによって「プレイヤー」になった水篠旬は、畑岡駅のインスタンスダンジョンで多くの「剛鉄牙のライカン」を狩り続け、レベルアップを果たした。",
      "レアリティ": "伝説+",
      "星": "4",
      "最大星": "6",
      "タイプ": "",
      "タイプID": "0",
      "射程": "",
      "武器タイプ": "",
      "未実装": true
    },
    "ステータス": {
      "物理攻撃力": "0",
      "魔法攻撃力": "122",
      "防御力": "47",
      "HP": "273",
      "敏捷性": "23",
      "クリティカル率": "50",
      "与クリティカルダメージ": "1500",
      "フェイタルヒット率": "0",
      "ブロック率": "0",
      "被ダメージ減少": 0,
      "デバフ回避妨害率": "0",
      "デバフ回避率": "0"
    },
    "成長データ": {
      "攻撃力タイプ": "魔法攻撃力",
      "レベル1": {
        "魔法攻撃力": 122,
        "防御力": 47,
        "HP": 273
      },
      "レベル30": {
        "魔法攻撃力": 557,
        "防御力": 221,
        "HP": 1230
      },
      "レベルアップ上昇値": {
        "魔法攻撃力": 15,
        "防御力": 6,
        "HP": 33
      },
      "強化上昇値": {
        "魔法攻撃力": 43,
        "防御力": 15,
        "HP": 96
      },
      "強化段階別": {
        "+0": {
          "魔法攻撃力": 557,
          "防御力": 221,
          "HP": 1230
        },
        "+1": {
          "魔法攻撃力": 600,
          "防御力": 236,
          "HP": 1326
        },
        "+2": {
          "魔法攻撃力": 643,
          "防御力": 251,
          "HP": 1422
        },
        "+3": {
          "魔法攻撃力": 686,
          "防御力": 266,
          "HP": 1518
        },
        "+4": {
          "魔法攻撃力": 729,
          "防御力": 281,
          "HP": 1614
        },
        "+5": {
          "魔法攻撃力": 772,
          "防御力": 296,
          "HP": 1710
        }
      },
      "強化コスト": [
        {
          "段階": 0,
          "コスト": 2800
        },
        {
          "段階": 1,
          "コスト": 3600
        },
        {
          "段階": 2,
          "コスト": 4400
        },
        {
          "段階": 3,
          "コスト": 5200
        },
        {
          "段階": 4,
          "コスト": 6000
        }
      ]
    },
    "経験値": {
      "最大レベル累計": 123900
    },
    "潜在能力解放": {
      "available": false
    },
    "スキル情報": {
      "通常攻撃": {
        "id": "10173401",
        "name": "",
        "desc": "敵1体\n - 魔法攻撃力の80%のダメージを1回与える\nスキル強化効果\n - ダメージ上昇：物理攻撃力の80%になる",
        "cooltime": "",
        "icon": "images/icon/SkillIcon_PC/Tex_Skill_1017301.webp"
      },
      "スキル1": {
        "id": "10173402",
        "name": "急所突き",
        "desc": "敵4体\nスキル強化効果\n - ダメージ上昇：物理攻撃力の47%になる",
        "cooltime": "⏱️ CT: 96秒",
        "icon": "images/icon/SkillIcon_PC/Tex_Skill_1017302.webp"
      },
      "スキル2": {
        "id": "10173403",
        "name": "影の召喚",
        "desc": "すべての敵\n - 魔法攻撃力の32%の防御無視ダメージを2回与える\nスキル強化効果\n - ダメージ上昇：物理攻撃力の32%になる",
        "cooltime": "⏱️ CT: 104秒",
        "icon": "images/icon/SkillIcon_PC/Tex_Skill_1017303.webp"
      },
      "パッシブ": {
        "id": "10173404",
        "name": "レベルアップ",
        "desc": "すべての味方\n - 与魔法ダメージ上昇[常時]\n自身\n - すべてのダメージ無効化[敵から攻撃を3回受けるまで]\n - 戦闘不能時、HPが40%の状態で復活(戦闘中1回のみ発動)\n - 逆境を勝ち抜いた者[常時]\n - デバフ回避率上昇[常時]\n - 自分の通常攻撃2回発動時、レベルが1上昇[最大30上昇]\n - 自分のスキル1回発動時、レベルが1上昇[最大30上昇]\n - 敵が戦闘不能時、レベルが2上昇[最大30上昇]\nスキル強化効果\n - 効果上昇：デバフ回避率上昇の効果が22%になる",
        "cooltime": "",
        "icon": "images/icon/SkillIcon_PC/Tex_Skill_1017304.webp"
      }
    },
    "超越解放効果": {},
    "プロフィール": {}
  }
]