[
  {
    "基本情報": {
      "ID": "310336",
      "名前": "デイジー(ナイトメア)",
      "サブネーム": "赤い蝶",
      "所属": "",
      "フレーバーテキスト": "真夜中に燃え盛るように羽ばたく赤い蝶。\\n蛾は光を求めて火に飛び込むが、赤い蝶は死をもたらすという。",
      "レアリティ": "伝説",
      "星": "6",
      "最大星": "6",
      "ロール": "魔法型",
      "射程": "遠距離",
      "武器タイプ": "魔法武器"
    },
    "ステータス": {
      "物理攻撃力": "0",
      "魔法攻撃力": "239",
      "防御力": "92",
      "HP": "535",
      "敏捷性": "29",
      "クリティカル率": "50",
      "与クリティカルダメージ": "1500",
      "フェイタルヒット率": "0",
      "ブロック率": "0",
      "被ダメージ減少": "0",
      "デバフ回避妨害率": "0",
      "デバフ回避率": "0"
    },
    "スキル情報": {
      "通常攻撃": {
        "名前": "",
        "説明": "敵1体\n - 魔法攻撃力の100%のダメージを1回与える\n - 火傷付与[確率100%][3ターン継続]\nスキル強化効果\n - ダメージ上昇：物理攻撃力の100%になる",
        "CT": "",
        "対象数": "1"
      },
      "スキル1": {
        "名前": "舞扇子",
        "説明": "敵1体\n - 魔法攻撃力の245%のダメージを1回与える\n - 火傷付与[確率100%][3ターン継続]\n - 味方2体\n - 減殺[10ターン継続]\nスキル強化効果\n - ダメージ上昇：物理攻撃力の245%になる",
        "CT": "⏱️ CT: 90秒",
        "対象数": "1"
      },
      "スキル2": {
        "名前": "炎扇",
        "説明": "すべての敵\n - 魔法攻撃力の120%の貫通ダメージを1回与える\n - 火傷付与[確率100%][3ターン継続]\n - 対象が[火傷]状態の場合、魔法攻撃力の900%の追加ダメージを与える\nスキル強化効果\n - ダメージ上昇：物理攻撃力の120%になる",
        "CT": "⏱️ CT: 70秒",
        "対象数": "5"
      },
      "パッシブ": {
        "名前": "炎蝶の舞",
        "説明": "すべての味方\n - 麻痺遮断[2ターン継続]\n - 自分の通常攻撃1回発動時、麻痺遮断[2ターン継続]\n - 自身\n - 自分のHPが最大HPの50%以下の場合、すべてのダメージ遮断[3ターン継続](戦闘中1回発動)",
        "CT": "",
        "対象数": "5"
      }
    },
    "超越解放効果": {
      "超越1段階解放効果": "",
      "超越2段階解放効果": "",
      "超越3段階解放効果": "",
      "超越4段階解放効果": "",
      "超越5段階解放効果": "",
      "超越6段階解放効果": "",
      "超越7段階解放効果": "",
      "超越8段階解放効果": "",
      "超越9段階解放効果": "",
      "超越10段階解放効果": "",
      "超越11段階解放効果": "",
      "超越12段階解放効果": ""
    },
    "プロフィール": {
      "CV": "",
      "種族": "",
      "性別": "",
      "血液型": "",
      "誕生日": "",
      "年齢": "",
      "身長": "",
      "体重": "",
      "星座": "",
      "好きなもの": "",
      "嫌いなもの": "",
      "ストーリー": "デイジーの弟であるエースは、若くして領主の座に就いた。\\nそんな折、月光の島の戦争に巻き込まれ、エースは敵にさらわれてしまう。\\n弟を助けるためにネコの妖怪と取引をしたデイジーは、陰陽術と力を手に入れるが、その代わりに体の一部が猫のように変わってしまった。\\n時が経ち、戦争で勝利したエースが領地を治め始めると、\\nデイジーは傍で彼を補佐した。\\n彼女は領主である弟に輝く光でいてほしかった。常に正義を貫いてほしかった。\\nだが、領地を治めるとなると、時には後ろ暗いことにも手を染めなければならない。\\nそのため、デイジーは月光守護団という団体を設立してエースを護衛させると同時に、エースの見えないところで、彼の正義に反するような裏の仕事はすべて自分が引き受けることにした。\\n彼女が夜の主と呼ばれるようになったのはそのためである。"
    }
  }
]